odoo/addons/stock_picking_report_summary/README.rst
odoo/addons/stock_picking_report_summary/__init__.py
odoo/addons/stock_picking_report_summary/__manifest__.py
odoo/addons/stock_picking_report_summary/i18n/fr.po
odoo/addons/stock_picking_report_summary/i18n/stock_picking_report_summary.pot
odoo/addons/stock_picking_report_summary/models/__init__.py
odoo/addons/stock_picking_report_summary/models/picking_summary_wizard.py
odoo/addons/stock_picking_report_summary/models/picking_summary_wizard_picking.py
odoo/addons/stock_picking_report_summary/models/picking_summary_wizard_product.py
odoo/addons/stock_picking_report_summary/readme/CONTRIBUTORS.rst
odoo/addons/stock_picking_report_summary/readme/DESCRIPTION.rst
odoo/addons/stock_picking_report_summary/readme/USAGE.rst
odoo/addons/stock_picking_report_summary/reports/report_paperformat.xml
odoo/addons/stock_picking_report_summary/reports/report_print_picking_summary.xml
odoo/addons/stock_picking_report_summary/reports/report_print_picking_summary_template.xml
odoo/addons/stock_picking_report_summary/static/description/icon.png
odoo/addons/stock_picking_report_summary/static/description/index.html
odoo/addons/stock_picking_report_summary/static/description/pdf_report.png
odoo/addons/stock_picking_report_summary/static/description/pdf_report_wo_prices.png
odoo/addons/stock_picking_report_summary/static/description/wizard.png
odoo/addons/stock_picking_report_summary/tests/__init__.py
odoo/addons/stock_picking_report_summary/tests/test_module.py
odoo/addons/stock_picking_report_summary/views/action.xml
odoo/addons/stock_picking_report_summary/views/view_picking_summary_wizard.xml
odoo12_addon_stock_picking_report_summary-12.0.1.1.0.dist-info/METADATA
odoo12_addon_stock_picking_report_summary-12.0.1.1.0.dist-info/WHEEL
odoo12_addon_stock_picking_report_summary-12.0.1.1.0.dist-info/top_level.txt
odoo12_addon_stock_picking_report_summary-12.0.1.1.0.dist-info/RECORD
